{"cameraMode":{"drawMode":0,"name":"Shaded","section":"Shading Mode"},"sceneLighting":true,"audioPlay":false,"sceneViewState":{"showFog":true,"showMaterialUpdate":false,"showSkybox":true,"showFlares":true,"showImageEffects":true,"showParticleSystems":true},"in2DMode":false,"pivot":{"x":-66.93335723876953,"y":-88.35228729248047,"z":247.15756225585938},"rotation":{"x":-0.17950089275836945,"y":0.1183248832821846,"z":-0.021752240136265756,"w":-0.9763948917388916},"size":404.2298583984375,"orthographic":false}